simple_vllm/__init__.py
simple_vllm/llm.py
simple_vllm-0.0.4.dist-info/licenses/LICENSE
simple_vllm-0.0.4.dist-info/METADATA
simple_vllm-0.0.4.dist-info/WHEEL
simple_vllm-0.0.4.dist-info/top_level.txt
simple_vllm-0.0.4.dist-info/RECORD
