Metadata-Version: 2.4
Name: simple_vllm
Version: 0.0.4
Summary: VLLM & Unsloth Wrapper for simple local inference.
Author-email: Nikolai Rozanov <nikolai.rozanov@gmail.com>
License:                     GNU GENERAL PUBLIC LICENSE
Project-URL: Homepage, https://github.com/ai-nikolai/simple_vllm
License-File: LICENSE
Requires-Dist: unsloth==2025.5.7
Requires-Dist: vllm==0.8.5.post1
Dynamic: license-file
